Workbook

Sheet European_Bank
A1: Year | B1: CustomerId. | C1: Surname | D1: CreditScore | E1: Geography | F1: Gender | G1: Age | H1: Tenure | I1: Balance | J1: NumOfProducts | K1: HasCrCard | L1: IsActiveMember | M1: EstimatedSalary | N1: Exited
A2: 2025 | B2: 15634602 | C2: Hargrave | D2: 619 | E2: France | F2: Female | G2: 42 | H2: 2 | I2: 0 | J2: 1 | K2: 1 | L2: 1 | M2: 101348.88 | N2: 1
A3: 2025 | B3: 15647311 | C3: Hill | D3: 608 | E3: Spain | F3: Female | G3: 41 | H3: 1 | I3: 83807.86 | J3: 1 | K3: 0 | L3: 1 | M3: 112542.58 | N3: 0
A4: 2025 | B4: 15619304 | C4: Onio | D4: 502 | E4: France | F4: Female | G4: 42 | H4: 8 | I4: 159660.8 | J4: 3 | K4: 1 | L4: 0 | M4: 113931.57 | N4: 1
A5: 2025 | B5: 15701354 | C5: Boni | D5: 699 | E5: France | F5: Female | G5: 39 | H5: 1 | I5: 0 | J5: 2 | K5: 0 | L5: 0 | M5: 93826.63 | N5: 0
A6: 2025 | B6: 15737888 | C6: Mitchell | D6: 850 | E6: Spain | F6: Female | G6: 43 | H6: 2 | I6: 125510.82 | J6: 1 | K6: 1 | L6: 1 | M6: 79084.1 | N6: 0
A7: 2025 | B7: 15574012 | C7: Chu | D7: 645 | E7: Spain | F7: Male | G7: 44 | H7: 8 | I7: 113755.78 | J7: 2 | K7: 1 | L7: 0 | M7: 149756.71 | N7: 1
A8: 2025 | B8: 15592531 | C8: Bartlett | D8: 822 | E8: France | F8: Male | G8: 50 | H8: 7 | I8: 0 | J8: 2 | K8: 1 | L8: 1 | M8: 10062.8 | N8: 0
A9: 2025 | B9: 15656148 | C9: Obinna | D9: 376 | E9: Germany | F9: Female | G9: 29 | H9: 4 | I9: 115046.74 | J9: 4 | K9: 1 | L9: 0 | M9: 119346.88 | N9: 1
A10: 2025 | B10: 15792365 | C10: He | D10: 501 | E10: France | F10: Male | G10: 44 | H10: 4 | I10: 142051.07 | J10: 2 | K10: 0 | L10: 1 | M10: 74940.5 | N10: 0
A11: 2025 | B11: 15592389 | C11: H? | D11: 684 | E11: France | F11: Male | G11: 27 | H11: 2 | I11: 134603.88 | J11: 1 | K11: 1 | L11: 1 | M11: 71725.73 | N11: 0
A12: 2025 | B12: 15767821 | C12: Bearce | D12: 528 | E12: France | F12: Male | G12: 31 | H12: 6 | I12: 102016.72 | J12: 2 | K12: 0 | L12: 0 | M12: 80181.12 | N12: 0
A13: 2025 | B13: 15737173 | C13: Andrews | D13: 497 | E13: Spain | F13: Male | G13: 24 | H13: 3 | I13: 0 | J13: 2 | K13: 1 | L13: 0 | M13: 76390.01 | N13: 0
... A10001: 2025 | B10001: 15628319 | C10001: Walker | D10001: 792 | E10001: France | F10001: Female | G10001: 28 | H10001: 4 | I10001: 130142.79 | J10001: 1 | K10001: 1 | L10001: 0 | M10001: 38190.78 | N10001: 0

Sheet Customer Analysis
A1: Customer churn Analysis
A3: Total customer | B3: =COUNTA(European_Bank!B2:B10001) -> 10000
A4: Churned Customer | B4: =SUM(European_Bank!N2:N10001) -> 2037
A5: Churn Rate | B5: =B4/B3 -> 0.2037
A6: Retained Customer | B6: =B3-B4 -> 7963
A7: Average Credit Score | B7: =AVERAGE(European_Bank!D2:D10001) -> 650.5288
A8: Average Age | B8: =AVERAGE(European_Bank!G2:G10001) -> 38.9218
A9: Average Balance | B9: =AVERAGE(European_Bank!I2:I10001) -> 76485.889
A10: Average Estimated Salary | B10: =AVERAGE(European_Bank!M2:M10001) -> 100090.24
A11: Average Tenure | B11: =AVERAGE((European_Bank!H2:H10001)) -> 5.0128
A12: Average Number of Products | B12: =AVERAGE(European_Bank!J2:J10001) -> 1.5302
A13: Active Members | B13: =SUM(European_Bank!L2:L10001) -> 5151
A14: Customer Credit Card | B14: =SUM(European_Bank!K2:K10001) -> 7055
A15: Customers by Geography
A16: France | B16: =COUNTIF(European_Bank!E2:E10001,"France") -> 5014
A17: Germany | B17: =COUNTIF(European_Bank!E2:E10001,"Germany") -> 2509
A18: Spain | B18: =COUNTIF(European_Bank!E2:E10001,"Spain") -> 2477
A19: Customer Gender Analysis
A20: Female | B20: =COUNTIF(European_Bank!F2:F10001,"Female") -> 4543
A21: Male | B21: =COUNTIF(European_Bank!F2:F10001,"Male") -> 5457
A22: Active Member Churn Analysis
A23: Active Member Churned | B23: =SUMPRODUCT(European_Bank!L2:L10001,European_Bank!N2:N10001) -> 735
A24: Total Active Member | B24: =SUM(European_Bank!L2:L10001) -> 5151
A25: Active Member churn Rate | B25: =B23/B24 -> 0.14269074
A26: Churned Customer by Geography
A27: France | B27: =COUNTIFS(European_Bank!E2:E10001,"France",European_Bank!N2:N10001,1) -> 810
A28: Germany | B28: =COUNTIFS(European_Bank!E2:E10001,"Germany",European_Bank!N2:N10001,1) -> 814
A29: Spain | B29: =COUNTIFS(European_Bank!E2:E10001,"Spain",European_Bank!N2:N10001,1) -> 413
A30: Churned Rate of Geography
A31: France | B31: =B27/B16 -> 0.16154767
A32: Germany | B32: =B28/B17 -> 0.32443204
A33: Spain | B33: =B29/B18 -> 0.16673395
A34: Churn Rate by Gender
A35: Female | B35: =COUNTIFS(European_Bank!F2:F10001,"Female",European_Bank!N2:N10001,1)/B20 -> 0.25071539
A36: Male | B36: =COUNTIFS(European_Bank!F2:F10001,"Male",European_Bank!N2:N10001,1)/B21 -> 0.16455928
A37: Churned Analysis by Active membership
A38: Inactive Members Churned | B38: =SUMPRODUCT((European_Bank!L2:L10001=0)*European_Bank!N2:N10001) -> 1302
A39: Total Inactive members | B39: =COUNTIF(European_Bank!L2:L10001,0) -> 4849
A40: Inactive Members Churned Rate | B40: =B38/B39 -> 0.26850897
A41: Churn Analysis By Number of Product
A42: 1 Product | B42: =COUNTIFS(European_Bank!J2:J10001,1,European_Bank!N2:N10001,1) -> 1409
A43: 2 Product | B43: =COUNTIFS(European_Bank!J2:J10001,2,European_Bank!N2:N10001,1) -> 348
A44: 3 Product | B44: =COUNTIFS(European_Bank!J2:J10001,3,European_Bank!N2:N10001,1) -> 220
A45: 4 Product | B45: =COUNTIFS(European_Bank!J2:J10001,4,European_Bank!N2:N10001,1) -> 60
A46: Churn Rate by Number of Product
A47: 1 Product | B47: =B42/COUNTIF(European_Bank!J2:J10001,1) -> 0.27714398
A48: 2 Product | B48: =B43/COUNTIF(European_Bank!J3:J10002,1) -> 0.068463506
A49: 3 Product | B49: =B44/COUNTIF(European_Bank!J4:J10003,1) -> 0.043290043
A50: 4 Product | B50: =B45/COUNTIF(European_Bank!J5:J10004,1) -> 0.011806375
A51: Churn Analysis by Credit Card
A52: Credit Card Holder Churned | B52: =SUMPRODUCT((European_Bank!K2:K10001=1)*(European_Bank!N2:Z10001=1)) -> 1424
A53: Total Credit Card Holder | B53: =SUM(European_Bank!K2:K10001) -> 7055
A54: Credit Card Holder Churned Rate | B54: =B52/B53 -> 0.20184266
A55: Churn Analysis by Age
A56: Age group 18-30 | B56: 148
A57: Age group 31-40 | B57: =COUNTIFS(European_Bank!G3:G10002,">=31",European_Bank!G3:G10002,"<=40",European_Bank!N3:N10002,1) -> 538
A58: Age group 41-50 | B58: =COUNTIFS(European_Bank!G4:G10003,">=41",European_Bank!G4:G10003,"<=50",European_Bank!N4:N10003,1) -> 787
A59: Age group 51-60 | B59: =COUNTIFS(European_Bank!G5:G10004,">=51",European_Bank!G5:G10004,"<=60",European_Bank!N5:N10004,1) -> 448
A60: Age Group 61+ | B60: =COUNTIFS(European_Bank!G6:G10005,">=61",European_Bank!G6:G10005,">=61",European_Bank!N6:N10005,1) -> 115
A61: Churn Rate by Age Group
A62: Age group 18-30 | B62: =B56/COUNTIFS(European_Bank!G2:G10001,">=18",European_Bank!G2:G10001,"<=30") -> 0.075203252
A63: Age group 31-40 | B63: =B57/COUNTIFS(European_Bank!G3:G10002,">=18",European_Bank!G3:G10002,"<=30") -> 0.27337398
A64: Age group 41-50 | B64: =B58/COUNTIFS(European_Bank!G4:G10003,">=41",European_Bank!G4:G10003,"<=50") -> 0.33951682
A65: Age group 51-60 | B65: =B59/COUNTIFS(European_Bank!G5:G10004,">=51",European_Bank!G5:G10004,"<=60") -> 0.5621079
A66: Age Group 61+ | B66: =B60/COUNTIFS(European_Bank!G5:G10005,">=61") -> 0.24784483
A67: Churn analysis By tenure
A68: 0-2 Years | B68: =COUNTIFS(European_Bank!H2:H10001,">=0",European_Bank!H2:H10001,"<=2",European_Bank!N2:N10001,1) -> 528
A69: 3-5 Years | B69: =COUNTIFS(European_Bank!H3:H10002,">=3",European_Bank!H3:H10002,"<=5",European_Bank!N3:N10002,1) -> 625
A70: 6-8 Years | B70: =COUNTIFS(European_Bank!H4:H10003,">=6",European_Bank!H4:H10003,"<=8",European_Bank!N4:N10003,1) -> 570
A71: 9-10 Years | B71: =COUNTIFS(European_Bank!H5:H10004,">=9",European_Bank!H5:H10004,"<=10",European_Bank!N5:N10004,1) -> 314
A72: Churn rate By tenure
A73: 0-2 Years | B73: =B68/COUNTIFS(European_Bank!H2:H10001,">=0",European_Bank!H2:H10001,"<=2") -> 0.21153846
A74: 3-5 Years | B74: =B69/COUNTIFS(European_Bank!H3:H10002,">=0",European_Bank!H3:H10002,"<=2") -> 0.250501
A75: 6-8 Years | B75: =B70/COUNTIFS(European_Bank!H4:H10003,">=0",European_Bank!H4:H10003,"<=2") -> 0.22854852
A76: 9-10 Years | B76: =B71/COUNTIFS(European_Bank!H5:H10004,">=0",European_Bank!H5:H10004,"<=2") -> 0.12590217
A77: Churn Analysis by Credit Score
A78: 300-500 | B78: =COUNTIFS(European_Bank!D2:D10001,">=300",European_Bank!D2:D10001,"<=500",European_Bank!N2:N10001,1) -> 152
A79: 501-600 | B79: =COUNTIFS(European_Bank!D3:D10002,">=501",European_Bank!D3:D10002,"<=600",European_Bank!N3:N10002,1) -> 513
A80: 601-700 | B80: =COUNTIFS(European_Bank!D4:D10003,">=601",European_Bank!D4:D10003,"<=700",European_Bank!N4:N10003,1) -> 752
A81: 701-800 | B81: =COUNTIFS(European_Bank!D5:D10004,">=701",European_Bank!D5:D10004,"<=800",European_Bank!N5:N10004,1) -> 492
A82: 801-850 | B82: =COUNTIFS(European_Bank!D6:D10005,">=801",European_Bank!D6:D10005,"<=850",European_Bank!N6:N10005,1) -> 127
A83: 851-900 | B83: =COUNTIFS(European_Bank!D2:D10001,">=851",European_Bank!D2:D10001,"<=900",European_Bank!N2:N10001,1) -> 0
A84: Churn Rate by Credit Score
A85: 300-500 | B85: =B78/COUNTIFS(European_Bank!D2:D10001,">=300",European_Bank!D2:D10001,"<=500") -> 0.23639191
A86: 501-600 | B86: =B79/COUNTIFS(European_Bank!D3:D10002,">=300",European_Bank!D3:D10002,"<=500") -> 0.79782271
A87: 601-700 | B87: =B80/COUNTIFS(European_Bank!D4:D10003,">=300",European_Bank!D4:D10003,"<=500") -> 1.1695179
A88: 701-800 | B88: =B81/COUNTIFS(European_Bank!D5:D10004,">=300",European_Bank!D5:D10004,"<=500") -> 0.7651633
A89: 801-850 | B89: =B82/COUNTIFS(European_Bank!D6:D10005,">=300",European_Bank!D6:D10005,"<=500") -> 0.19751166
A90: 851-900 | B90: =B83/COUNTIFS(European_Bank!D7:D10006,">=300",European_Bank!D7:D10006,"<=500") -> 0
A91: Churn Analysis By Balance
A92: 0-25000 | B92: =COUNTIFS(European_Bank!I2:I10001,">=0",European_Bank!I2:I10001,"<=25000",European_Bank!N2:N10001,1) -> 504
A93: 25001-50000 | B93: =COUNTIFS(European_Bank!I3:I10002,">=25001",European_Bank!I3:I10002,"<=50000",European_Bank!N3:N10002,1) -> 22
A94: 50001-75000 | B94: =COUNTIFS(European_Bank!I4:I10003,">=50001",European_Bank!I4:I10003,"<=70000",European_Bank!N4:N10003,1) -> 55
A95: 75001-100000 | B95: =COUNTIFS(European_Bank!I5:I10004,">=75001",European_Bank!I5:I10004,"<=100000",European_Bank!N5:N10004,1) -> 225
A96: 100001-150000 | B96: =COUNTIFS(European_Bank!I6:I10005,">=100001",European_Bank!I6:I10005,"<=150000",European_Bank!N6:N10005,1) -> 987
A97: 150001+ | B97: =COUNTIFS(European_Bank!I2:I10001,">=150001",European_Bank!N2:N10001,1) -> 224
A98: Churned Rate by Balance
A99: 0-25000 | B99: =B92/COUNTIFS(European_Bank!I2:I10001,">=0",European_Bank!I2:I10001,"<=25000") -> 0.13911123
A100: 25001-75000 | B100: =B93/COUNTIFS(European_Bank!I3:I10002,">=25001",European_Bank!I3:I10002,"<=75000") -> 0.052631579
A101: 75001-100000 | B101: =B95/COUNTIFS(European_Bank!I4:I10003,">=75001",European_Bank!I4:I10003,"<=100000") -> 0.19413287
...

Sheet Visualization
A1: Customer Churn Visualization
A3: Churn Rate By Geography | B3: Churn Rate
A4: France | B4: ='Customer Analysis'!B31 -> 0.16154767
A5: Germany | B5: ='Customer Analysis'!B32 -> 0.32443204
A6: Spain | B6: ='Customer Analysis'!B33 -> 0.16673395
A19: Churn Rate By Gender | B19: Churn Rate
A20: Female | B20: ='Customer Analysis'!B35 -> 0.25071539
A21: Male | B21: ='Customer Analysis'!B36 -> 0.16455928
A29: Churn rate by active membership | B29: churn rate
A30: Active member | B30: ='Customer Analysis'!B25 -> 0.14269074
A31: Inactive Member | B31: ='Customer Analysis'!B40 -> 0.26850897
A42: Churn rate by Number of Products | B42: Churn Rate
A43: 1 Product | B43: ='Customer Analysis'!B47 -> 0.27714398
A44: 2 Product | B44: ='Customer Analysis'!B48 -> 0.068463506
A45: 3 Product | B45: ='Customer Analysis'!B49 -> 0.043290043
A46: 4 Product | B46: ='Customer Analysis'!B50 -> 0.011806375
A56: Churn Analysis by Credit Card | B56: Churn Rate
A57: Credit card holder | B57: ='Customer Analysis'!B54 -> 0.20184266
A58: No Credit Card | B58: =COUNTIFS(European_Bank!K2:K10001,0,European_Bank!N2:N10001,1)/COUNTIF(European_Bank!K2:K10001,0) -> 0.20814941
A68: Churn Rate by Age Group | B68: Churn Rate
A69: Age group 18-30 | B69: ='Customer Analysis'!B62 -> 0.075203252
A70: Age group 31-40 | B70: ='Customer Analysis'!B63 -> 0.27337398
A71: Age group 41-50 | B71: ='Customer Analysis'!B64 -> 0.33951682
A72: Age group 51-60 | B72: ='Customer Analysis'!B65 -> 0.5621079
A73: Age Group 61+ | B73: ='Customer Analysis'!B66 -> 0.24784483
